{
  "applications": [
    {
      "name": "TrackIT Third Party 1.0.0.0",
      "installerPath": "\\\\persvr02\\trackit$\\TrackIT_Live\\Config\\Installer\\NEW\\Setup TrackIT Third Party.exe",
      "silentArgs": "/install",
      "detectName": "TrackIT Third Party 1.0.0.0"
    },
    {
      "name": "TrackIT App",
      "installerPath": "\\\\persvr02\\trackit$\\TrackIT_Live\\Config\\Installer\\NEW\\TrackIT.application",
      "silentArgs": "/install",
      "detectName": "TrackIT App"
    },
    {
      "name": "Microsoft 365 Apps for enterprise - en-us",
      "installerPath": "\\\\persvr02\\trackit$\\0_Installer\\OfficeSetup.exe",
      "silentArgs": "/install",
      "detectName": "Microsoft 365 Apps for enterprise - en-us"
    },
    {
      "name": "Google Chrome",
      "installerPath": "\\\\persvr02\\trackit$\\0_Installer\\ChromeSetup.exe",
      "silentArgs": "/install",
      "detectName": "Google Chrome"
    }
  ]
}